cjm_byte_track/__init__.py
cjm_byte_track/_modidx.py
cjm_byte_track/basetrack.py
cjm_byte_track/byte_tracker.py
cjm_byte_track/core.py
cjm_byte_track/kalman_filter.py
cjm_byte_track/matching.py
cjm_byte_track/strack.py
cjm_byte_track-0.0.6.dist-info/LICENSE
cjm_byte_track-0.0.6.dist-info/METADATA
cjm_byte_track-0.0.6.dist-info/WHEEL
cjm_byte_track-0.0.6.dist-info/entry_points.txt
cjm_byte_track-0.0.6.dist-info/top_level.txt
cjm_byte_track-0.0.6.dist-info/RECORD
